{
  "fill" : {
    "automatic-gradient" : "extended-srgb:0.00000,0.53333,1.00000,1.00000"
  },
  "groups" : [
    {
      "layers" : [

      ],
      "shadow" : {
        "kind" : "neutral",
        "opacity" : 0.5
      },
      "translucency" : {
        "enabled" : true,
        "value" : 0.5
      }
    },
    {
      "layers" : [
        {
          "image-name" : "dark_2k_banner 2.png",
          "name" : "dark_2k_banner 2",
          "position" : {
            "scale" : 1,
            "translation-in-points" : [
              58.4140625,
              0
            ]
          }
        }
      ],
      "shadow" : {
        "kind" : "neutral",
        "opacity" : 0.5
      },
      "translucency" : {
        "enabled" : true,
        "value" : 0.5
      }
    }
  ],
  "supported-platforms" : {
    "squares" : "shared"
  }
}